superide/__init__.py
superide/__main__.py
superide/app.py
superide/cache.py
superide/cli.py
superide/compat.py
superide/exception.py
superide/fs.py
superide/http.py
superide/lockfile.py
superide/maintenance.py
superide/proc.py
superide/public.py
superide/telemetry.py
superide/util.py
superide/boards/__init__.py
superide/boards/boards.json
superide/boards/cli.py
superide/boards/__pycache__/__init__.cpython-312.pyc
superide/boards/__pycache__/cli.cpython-312.pyc
superide/debug/__init__.py
superide/debug/cli.py
superide/debug/exception.py
superide/debug/helpers.py
superide/debug/config/__init__.py
superide/debug/config/base.py
superide/debug/config/blackmagic.py
superide/debug/config/factory.py
superide/debug/config/generic.py
superide/debug/config/jlink.py
superide/debug/config/mspdebug.py
superide/debug/config/native.py
superide/debug/config/qemu.py
superide/debug/config/renode.py
superide/debug/process/__init__.py
superide/debug/process/base.py
superide/debug/process/client.py
superide/debug/process/gdb.py
superide/debug/process/server.py
superide/home/__init__.py
superide/home/app.py
superide/home/cli.py
superide/home/runServer.py
superide/home/rpc/__init__.py
superide/home/rpc/handlers/__init__.py
superide/home/rpc/handlers/app.py
superide/home/rpc/handlers/base.py
superide/home/rpc/handlers/ide.py
superide/home/rpc/handlers/os.py
superide/home/rpc/handlers/project.py
superide/home/rpc/handlers/registry.py
superide/home/static/favicon.ico
superide/home/static/index.html
superide/home/static/assets/favicon.ico
superide/home/static/assets/index-6fed80ed.css
superide/home/static/assets/index-8630f54e.css
superide/home/static/assets/index-9ab32a3b.js
superide/home/static/assets/index-d2bbbc6e.js
superide/home/static/assets/logo-b2ff5bfc.png
superide/project/__init__.py
superide/project/cli.py
superide/project/config.py
superide/project/exception.py
superide/project/helpers.py
superide/project/options.py
superide/project/savedeps.py
superide/project/vcsclient.py
super_ide-1.5.1.dist-info/LICENSE
super_ide-1.5.1.dist-info/METADATA
super_ide-1.5.1.dist-info/WHEEL
super_ide-1.5.1.dist-info/entry_points.txt
super_ide-1.5.1.dist-info/top_level.txt
super_ide-1.5.1.dist-info/RECORD
