Metadata-Version: 2.1
Name: super-ide
Version: 1.5.1
Summary: A professional Cross-platform IDE. Cross-platform IDE and Unified Debugger. Static Code Analyzer and Remote Unit Testing. Multi-platform and Multi-architecture Build System. Firmware File Explorer and Memory Inspection. IoT, Arduino, CMSIS, ESP-IDF, FreeRTOS, libOpenCM3, mbedOS, Pulp OS, SPL, STM32Cube, Zephyr RTOS, ARM, AVR, Espressif (ESP8266/ESP32), FPGA, MCS-51 (8051), MSP430, Nordic (nRF51/nRF52), NXP i.MX RT, PIC32, RISC-V, STMicroelectronics (STM8/STM32), Teensy
Home-page: https://mengning.com.cn
Author: Mengning Software
Author-email: contact@mengning.com.cn
License: AGPL-3.0 License
Keywords: iot,embedded,arduino,mbed,esp8266,esp32,fpga,firmware,continuous-integration,cloud-ide,avr,arm,ide,unit-testing,hardware,verilog,microcontroller,debug
Classifier: Development Status :: 5 - Production/Stable
Classifier: Environment :: Console
Classifier: Intended Audience :: Developers
Classifier: License :: OSI Approved :: Apache Software License
Classifier: Operating System :: OS Independent
Classifier: Programming Language :: C
Classifier: Programming Language :: Python
Classifier: Programming Language :: Python :: 3
Classifier: Topic :: Software Development
Classifier: Topic :: Software Development :: Build Tools
Classifier: Topic :: Software Development :: Compilers
Requires-Python: >=3.6
License-File: LICENSE
Requires-Dist: bottle ==0.12.*
Requires-Dist: colorama
Requires-Dist: pyelftools ==0.29
Requires-Dist: pyserial ==3.5.*
Requires-Dist: requests ==2.*
Requires-Dist: semantic-version ==2.10.*
Requires-Dist: tabulate ==0.*
Requires-Dist: Flask ==3.0.0
Requires-Dist: Flask-SocketIO ==5.3.6
Requires-Dist: GitPython >=3.1.40
Requires-Dist: click ==8.0.4 ; python_version < "3.7"
Requires-Dist: marshmallow ==3.14.1 ; python_version < "3.7"
Requires-Dist: click ==8.1.* ; python_version >= "3.7"
Requires-Dist: marshmallow ==3.19.* ; python_version >= "3.7"
